aiokraken/__init__.py
aiokraken/rest/__init__.py
aiokraken/rest/client.py
aiokraken/utils/__init__.py
aiokraken/websockets/__init__.py
aiokraken/websockets/client.py
aiokraken-2.0.0.dist-info/LICENSE
aiokraken-2.0.0.dist-info/METADATA
aiokraken-2.0.0.dist-info/WHEEL
aiokraken-2.0.0.dist-info/top_level.txt
aiokraken-2.0.0.dist-info/RECORD
