Metadata-Version: 2.1
Name: aiokraken
Version: 2.0.0
Summary: Python client library for the Kraken Rest and Websocket API using asyncio and aiohttp
Home-page: https://github.com/dantimofte/aiokraken
Author: Dan Timofte
Author-email: dan@arcane.no
License: UNKNOWN
Platform: UNKNOWN
Requires-Dist: aiohttp
Requires-Dist: aiodns
Requires-Dist: cchardet
